{
    "data": {
        "allQuestionsCount": [
            {
                "difficulty": "All",
                "count": 3555
            },
            {
                "difficulty": "Easy",
                "count": 877
            },
            {
                "difficulty": "Medium",
                "count": 1843
            },
            {
                "difficulty": "Hard",
                "count": 835
            }
        ],
        "userContestRanking": {
            "attendedContestsCount": 5,
            "rating": 1669.03,
            "globalRanking": 105641,
            "totalParticipants": 697019,
            "topPercentage": 15.51,
            "badge": null
        },
        "matchedUser": {
            "username": "mahathibodela7",
            "submitStats": {
                "acSubmissionNum": [
                    {
                        "difficulty": "All",
                        "count": 486,
                        "submissions": 1055
                    },
                    {
                        "difficulty": "Easy",
                        "count": 87,
                        "submissions": 189
                    },
                    {
                        "difficulty": "Medium",
                        "count": 327,
                        "submissions": 692
                    },
                    {
                        "difficulty": "Hard",
                        "count": 72,
                        "submissions": 174
                    }
                ]
            }
        }
    }
}